{
  "main": {
    "id": "e082f2c096456c7c",
    "type": "split",
    "children": [
      {
        "id": "7d7fc25aebbb901f",
        "type": "tabs",
        "children": [
          {
            "id": "07af7e6e2ead544d",
            "type": "leaf",
            "state": {
              "type": "markdown",
              "state": {
                "file": "AWS/AWS Lambda.md",
                "mode": "source",
                "source": false
              }
            }
          },
          {
            "id": "6aaae0a3359053a2",
            "type": "leaf",
            "state": {
              "type": "markdown",
              "state": {
                "file": "Daily/05-MAIO/2024-05-27.md",
                "mode": "source",
                "source": false
              }
            }
          }
        ],
        "currentTab": 1
      }
    ],
    "direction": "vertical"
  },
  "left": {
    "id": "07f11e053d9bf175",
    "type": "split",
    "children": [
      {
        "id": "7896ddc7180d3576",
        "type": "tabs",
        "children": [
          {
            "id": "4ee2eb6c24704379",
            "type": "leaf",
            "state": {
              "type": "file-explorer",
              "state": {
                "sortOrder": "alphabetical"
              }
            }
          },
          {
            "id": "84bb971a536dda4c",
            "type": "leaf",
            "state": {
              "type": "search",
              "state": {
                "query": "",
                "matchingCase": false,
                "explainSearch": false,
                "collapseAll": false,
                "extraContext": false,
                "sortOrder": "alphabetical"
              }
            }
          },
          {
            "id": "acd3095ffd0b86cf",
            "type": "leaf",
            "state": {
              "type": "bookmarks",
              "state": {}
            }
          }
        ]
      }
    ],
    "direction": "horizontal",
    "width": 225.5
  },
  "right": {
    "id": "9d188c02af334e54",
    "type": "split",
    "children": [
      {
        "id": "b8e4a659b6bf37a3",
        "type": "tabs",
        "children": [
          {
            "id": "bd79437e5319f98b",
            "type": "leaf",
            "state": {
              "type": "backlink",
              "state": {
                "file": "Daily/05-MAIO/2024-05-27.md",
                "collapseAll": false,
                "extraContext": false,
                "sortOrder": "alphabetical",
                "showSearch": false,
                "searchQuery": "",
                "backlinkCollapsed": false,
                "unlinkedCollapsed": true
              }
            }
          },
          {
            "id": "900e1cbec90687a1",
            "type": "leaf",
            "state": {
              "type": "outgoing-link",
              "state": {
                "file": "Daily/05-MAIO/2024-05-27.md",
                "linksCollapsed": false,
                "unlinkedCollapsed": true
              }
            }
          },
          {
            "id": "54e6b9b38bf774b3",
            "type": "leaf",
            "state": {
              "type": "tag",
              "state": {
                "sortOrder": "frequency",
                "useHierarchy": true
              }
            }
          },
          {
            "id": "089cacd9ab915c36",
            "type": "leaf",
            "state": {
              "type": "outline",
              "state": {
                "file": "Daily/05-MAIO/2024-05-27.md"
              }
            }
          }
        ],
        "currentTab": 2
      }
    ],
    "direction": "horizontal",
    "width": 300,
    "collapsed": true
  },
  "left-ribbon": {
    "hiddenItems": {
      "switcher:Abrir a troca rápida": false,
      "graph:Abrir visualização em gráfico": false,
      "canvas:Criar novo canvas": false,
      "daily-notes:Abrir a nota de hoje": false,
      "templates:Inserir modelo": false,
      "command-palette:Abrir paleta de comandos": false,
      "table-editor-obsidian:Advanced Tables Toolbar": false
    }
  },
  "active": "6aaae0a3359053a2",
  "lastOpenFiles": [
    "Daily/05-MAIO/2024-05-24.md",
    "Daily/05-MAIO/2024-05-27.md",
    "AWS/AWS Lambda.md",
    "Tópicos de Estudo.md",
    "AWS/Amazon CloudFront.md",
    "AWS/AWS IAM.md",
    "AWS/Amazon ECS.md",
    "Dicty/QuickNotes/Injeção de SQL.md",
    "Dicty/ETL.md",
    "Dicty/Container.md",
    "AWS/AWS CloudWatch.md",
    "AWS/VPC.md",
    "Dicty/WAF.md",
    "Dicty/QuickNotes/Cross-site-scripting (XSS).md",
    "Dicty/QuickNotes/DDoS.md",
    "Dicty/Firewall.md",
    "AWS/Amazon S3.md",
    "Daily/05-MAIO/2024-05-23.md",
    "Daily/05-MAIO/2024-05-22.md",
    "Dicty/QuickNotes/TLD.md",
    "Dicty/QuickNotes/Proxy reverso.md",
    "Dicty/QuickNotes/Ferramentas de Gestão de Identidade.md",
    "Dicty/QuickNotes/Falsificação de solicitação de sites.md",
    "Dicty/QuickNotes/Computação de borda.md",
    "AWS/Amazon ECR.md",
    "AWS/Elastic Load Balancing.md",
    "Dicty/QuickNotes",
    "IMGS/DNS/dnsExample.png",
    "IMGS/DNS",
    "Pasted image 20240522172905.png",
    "Conceito CI",
    "Dicty/FastNotes",
    "Dicty/FastNotes",
    "Sem título.canvas",
    "IMGS/CICD/Pasted image 20240517160807.png",
    "IMGS/CICD",
    "IMGS",
    "Daily/05-MAIO",
    "Templates",
    "Templates",
    "Pasted image 20240516155546.png"
  ]
}